[{"day":"2011-12-09","open":"0.795","high":"0.814","low":"0.795","close":"0.797","volume":"106177232"},{"day":"2011-12-16","open":"0.790","high":"0.803","low":"0.747","close":"0.781","volume":"334099288"},{"day":"2011-12-23","open":"0.775","high":"0.800","low":"0.730","close":"0.761","volume":"392913976"},{"day":"2011-12-30","open":"0.759","high":"0.773","low":"0.703","close":"0.729","volume":"382534892"},{"day":"2012-01-06","open":"0.735","high":"0.739","low":"0.647","close":"0.670","volume":"241225648"},{"day":"2012-01-13","open":"0.667","high":"0.731","low":"0.658","close":"0.668","volume":"670387320"},{"day":"2012-01-20","open":"0.656","high":"0.670","low":"0.615","close":"0.648","volume":"615930496"},{"day":"2012-02-03","open":"0.649","high":"0.685","low":"0.638","close":"0.682","volume":"483010308"},{"day":"2012-02-10","open":"0.683","high":"0.708","low":"0.671","close":"0.701","volume":"669537448"},{"day":"2012-02-17","open":"0.694","high":"0.734","low":"0.691","close":"0.719","volume":"372557260"},{"day":"2012-02-24","open":"0.725","high":"0.768","low":"0.716","close":"0.764","volume":"570327924"},{"day":"2012-03-02","open":"0.764","high":"0.774","low":"0.733","close":"0.759","volume":"433948984"},{"day":"2012-03-09","open":"0.760","high":"0.780","low":"0.740","close":"0.779","volume":"325818276"},{"day":"2012-03-16","open":"0.783","high":"0.802","low":"0.735","close":"0.767","volume":"496190204"},{"day":"2012-03-23","open":"0.764","high":"0.783","low":"0.735","close":"0.740","volume":"351690708"},{"day":"2012-03-30","open":"0.738","high":"0.748","low":"0.677","close":"0.683","volume":"197437054"},{"day":"2012-04-06","open":"0.680","high":"0.708","low":"0.678","close":"0.703","volume":"115370228"},{"day":"2012-04-13","open":"0.701","high":"0.728","low":"0.675","close":"0.722","volume":"244235628"},{"day":"2012-04-20","open":"0.715","high":"0.732","low":"0.708","close":"0.729","volume":"313232288"},{"day":"2012-04-27","open":"0.725","high":"0.725","low":"0.664","close":"0.688","volume":"325421092"},{"day":"2012-05-04","open":"0.696","high":"0.719","low":"0.689","close":"0.719","volume":"209174012"},{"day":"2012-05-11","open":"0.717","high":"0.743","low":"0.714","close":"0.722","volume":"410653088"},{"day":"2012-05-18","open":"0.728","high":"0.735","low":"0.707","close":"0.712","volume":"274839508"},{"day":"2012-05-25","open":"0.712","high":"0.723","low":"0.703","close":"0.706","volume":"220311312"},{"day":"2012-06-01","open":"0.701","high":"0.747","low":"0.690","close":"0.739","volume":"321618960"},{"day":"2012-06-08","open":"0.727","high":"0.741","low":"0.715","close":"0.721","volume":"161295784"},{"day":"2012-06-15","open":"0.721","high":"0.757","low":"0.720","close":"0.747","volume":"412830336"},{"day":"2012-06-21","open":"0.755","high":"0.763","low":"0.737","close":"0.744","volume":"195424400"},{"day":"2012-06-29","open":"0.740","high":"0.742","low":"0.710","close":"0.734","volume":"318629170"},{"day":"2012-07-06","open":"0.740","high":"0.758","low":"0.718","close":"0.745","volume":"360352608"},{"day":"2012-07-13","open":"0.740","high":"0.743","low":"0.713","close":"0.730","volume":"281225000"},{"day":"2012-07-20","open":"0.730","high":"0.730","low":"0.688","close":"0.710","volume":"234041088"},{"day":"2012-07-27","open":"0.701","high":"0.723","low":"0.701","close":"0.709","volume":"170417822"},{"day":"2012-08-03","open":"0.708","high":"0.719","low":"0.678","close":"0.719","volume":"332773506"},{"day":"2012-08-10","open":"0.714","high":"0.750","low":"0.712","close":"0.748","volume":"240593824"},{"day":"2012-08-17","open":"0.746","high":"0.747","low":"0.717","close":"0.727","volume":"201537040"},{"day":"2012-08-24","open":"0.719","high":"0.762","low":"0.717","close":"0.739","volume":"342081052"},{"day":"2012-08-31","open":"0.736","high":"0.741","low":"0.697","close":"0.713","volume":"513309128"},{"day":"2012-09-07","open":"0.710","high":"0.776","low":"0.705","close":"0.766","volume":"378314972"},{"day":"2012-09-14","open":"0.768","high":"0.771","low":"0.745","close":"0.748","volume":"239194680"},{"day":"2012-09-21","open":"0.746","high":"0.746","low":"0.694","close":"0.694","volume":"320319372"},{"day":"2012-09-28","open":"0.690","high":"0.702","low":"0.664","close":"0.696","volume":"480841982"},{"day":"2012-10-12","open":"0.690","high":"0.729","low":"0.680","close":"0.711","volume":"241205896"},{"day":"2012-10-19","open":"0.712","high":"0.727","low":"0.697","close":"0.723","volume":"228250866"},{"day":"2012-10-26","open":"0.717","high":"0.730","low":"0.683","close":"0.688","volume":"114524646"},{"day":"2012-11-02","open":"0.688","high":"0.708","low":"0.685","close":"0.705","volume":"88217113"},{"day":"2012-11-09","open":"0.705","high":"0.707","low":"0.676","close":"0.678","volume":"51604558"},{"day":"2012-11-16","open":"0.679","high":"0.685","low":"0.658","close":"0.661","volume":"46079749"},{"day":"2012-11-23","open":"0.661","high":"0.668","low":"0.650","close":"0.656","volume":"89383221"},{"day":"2012-11-30","open":"0.656","high":"0.656","low":"0.604","close":"0.608","volume":"133558184"},{"day":"2012-12-07","open":"0.608","high":"0.642","low":"0.589","close":"0.641","volume":"248190608"},{"day":"2012-12-14","open":"0.641","high":"0.663","low":"0.632","close":"0.661","volume":"230715294"},{"day":"2012-12-21","open":"0.661","high":"0.674","low":"0.647","close":"0.671","volume":"181885310"},{"day":"2012-12-28","open":"0.668","high":"0.715","low":"0.667","close":"0.709","volume":"210846988"},{"day":"2013-01-04","open":"0.711","high":"0.721","low":"0.700","close":"0.708","volume":"66465520"},{"day":"2013-01-11","open":"0.703","high":"0.747","low":"0.702","close":"0.731","volume":"245574448"},{"day":"2013-01-18","open":"0.730","high":"0.790","low":"0.730","close":"0.790","volume":"287426672"},{"day":"2013-01-25","open":"0.790","high":"0.795","low":"0.752","close":"0.763","volume":"228657732"},{"day":"2013-02-01","open":"0.764","high":"0.797","low":"0.764","close":"0.783","volume":"190447152"},{"day":"2013-02-08","open":"0.784","high":"0.825","low":"0.766","close":"0.822","volume":"355864896"},{"day":"2013-02-22","open":"0.827","high":"0.853","low":"0.814","close":"0.835","volume":"387963596"},{"day":"2013-03-01","open":"0.833","high":"0.885","low":"0.833","close":"0.885","volume":"335081892"},{"day":"2013-03-08","open":"0.878","high":"0.904","low":"0.849","close":"0.863","volume":"354957192"},{"day":"2013-03-15","open":"0.859","high":"0.871","low":"0.817","close":"0.853","volume":"248626812"},{"day":"2013-03-22","open":"0.848","high":"0.886","low":"0.826","close":"0.878","volume":"274650772"},{"day":"2013-03-29","open":"0.882","high":"0.884","low":"0.855","close":"0.860","volume":"189786884"},{"day":"2013-04-03","open":"0.861","high":"0.884","low":"0.825","close":"0.829","volume":"80162304"},{"day":"2013-04-12","open":"0.821","high":"0.864","low":"0.815","close":"0.844","volume":"96923884"},{"day":"2013-04-19","open":"0.844","high":"0.897","low":"0.821","close":"0.891","volume":"153623006"},{"day":"2013-04-26","open":"0.891","high":"0.937","low":"0.882","close":"0.890","volume":"274804328"},{"day":"2013-05-03","open":"0.887","high":"0.939","low":"0.878","close":"0.938","volume":"90019148"},{"day":"2013-05-10","open":"0.940","high":"0.993","low":"0.938","close":"0.987","volume":"233413964"},{"day":"2013-05-17","open":"0.985","high":"1.034","low":"0.964","close":"1.017","volume":"451143884"},{"day":"2013-05-24","open":"1.017","high":"1.074","low":"1.016","close":"1.070","volume":"391921516"},{"day":"2013-05-31","open":"1.066","high":"1.089","low":"1.046","close":"1.067","volume":"314504588"},{"day":"2013-06-07","open":"1.060","high":"1.070","low":"1.007","close":"1.032","volume":"235564168"},{"day":"2013-06-14","open":"1.018","high":"1.070","low":"0.981","close":"1.069","volume":"134797900"},{"day":"2013-06-21","open":"1.073","high":"1.090","low":"0.985","close":"1.027","volume":"394461276"},{"day":"2013-06-28","open":"1.016","high":"1.064","low":"0.902","close":"1.003","volume":"600963888"},{"day":"2013-07-05","open":"1.002","high":"1.107","low":"1.000","close":"1.052","volume":"1162438336"},{"day":"2013-07-12","open":"1.024","high":"1.119","low":"1.011","close":"1.092","volume":"837381920"},{"day":"2013-07-19","open":"1.088","high":"1.153","low":"1.088","close":"1.106","volume":"1161364000"},{"day":"2013-07-26","open":"1.099","high":"1.203","low":"1.099","close":"1.152","volume":"1345926576"},{"day":"2013-08-02","open":"1.143","high":"1.193","low":"1.084","close":"1.169","volume":"1412968304"},{"day":"2013-08-09","open":"1.167","high":"1.206","low":"1.137","close":"1.161","volume":"999831920"},{"day":"2013-08-16","open":"1.159","high":"1.172","low":"1.117","close":"1.117","volume":"944099496"},{"day":"2013-08-23","open":"1.112","high":"1.211","low":"1.110","close":"1.198","volume":"964497232"},{"day":"2013-08-30","open":"1.202","high":"1.234","low":"1.162","close":"1.171","volume":"722355688"},{"day":"2013-09-06","open":"1.170","high":"1.269","low":"1.164","close":"1.262","volume":"553484160"},{"day":"2013-09-13","open":"1.262","high":"1.265","low":"1.188","close":"1.235","volume":"615904308"},{"day":"2013-09-18","open":"1.231","high":"1.276","low":"1.231","close":"1.265","volume":"524136976"},{"day":"2013-09-27","open":"1.266","high":"1.324","low":"1.266","close":"1.308","volume":"672294112"},{"day":"2013-09-30","open":"1.314","high":"1.350","low":"1.310","close":"1.346","volume":"96413992"},{"day":"2013-10-11","open":"1.350","high":"1.399","low":"1.333","close":"1.360","volume":"513256400"},{"day":"2013-10-18","open":"1.360","high":"1.387","low":"1.294","close":"1.332","volume":"683824112"},{"day":"2013-10-25","open":"1.333","high":"1.382","low":"1.231","close":"1.252","volume":"782200624"},{"day":"2013-11-01","open":"1.252","high":"1.269","low":"1.176","close":"1.199","volume":"802844408"},{"day":"2013-11-08","open":"1.195","high":"1.254","low":"1.181","close":"1.189","volume":"856667760"},{"day":"2013-11-15","open":"1.185","high":"1.264","low":"1.168","close":"1.247","volume":"742482984"},{"day":"2013-11-22","open":"1.251","high":"1.288","low":"1.249","close":"1.268","volume":"543642640"},{"day":"2013-11-29","open":"1.260","high":"1.344","low":"1.255","close":"1.341","volume":"454797056"},{"day":"2013-12-06","open":"1.270","high":"1.293","low":"1.172","close":"1.186","volume":"826522216"},{"day":"2013-12-13","open":"1.187","high":"1.262","low":"1.186","close":"1.251","volume":"617106920"},{"day":"2013-12-20","open":"1.252","high":"1.269","low":"1.220","close":"1.230","volume":"616797112"},{"day":"2013-12-27","open":"1.225","high":"1.275","low":"1.200","close":"1.273","volume":"560300328"},{"day":"2014-01-03","open":"1.273","high":"1.328","low":"1.260","close":"1.325","volume":"486881776"},{"day":"2014-01-10","open":"1.324","high":"1.394","low":"1.285","close":"1.324","volume":"814413704"},{"day":"2014-01-17","open":"1.323","high":"1.399","low":"1.321","close":"1.367","volume":"587093432"},{"day":"2014-01-24","open":"1.361","high":"1.464","low":"1.332","close":"1.453","volume":"854377112"},{"day":"2014-01-30","open":"1.448","high":"1.480","low":"1.413","close":"1.463","volume":"581302376"},{"day":"2014-02-07","open":"1.451","high":"1.500","low":"1.450","close":"1.498","volume":"144614288"},{"day":"2014-02-14","open":"1.505","high":"1.526","low":"1.441","close":"1.479","volume":"905228528"},{"day":"2014-02-21","open":"1.483","high":"1.524","low":"1.467","close":"1.483","volume":"1152069312"},{"day":"2014-02-28","open":"1.481","high":"1.534","low":"1.360","close":"1.400","volume":"1538857296"},{"day":"2014-03-07","open":"1.400","high":"1.441","low":"1.389","close":"1.428","volume":"907849240"},{"day":"2014-03-14","open":"1.408","high":"1.412","low":"1.344","close":"1.398","volume":"1042254536"},{"day":"2014-03-21","open":"1.401","high":"1.456","low":"1.346","close":"1.382","volume":"996297712"},{"day":"2014-03-28","open":"1.375","high":"1.389","low":"1.283","close":"1.292","volume":"785273544"},{"day":"2014-04-04","open":"1.293","high":"1.327","low":"1.280","close":"1.314","volume":"930162800"},{"day":"2014-04-11","open":"1.295","high":"1.363","low":"1.291","close":"1.329","volume":"695967184"},{"day":"2014-04-18","open":"1.329","high":"1.346","low":"1.317","close":"1.344","volume":"400805068"},{"day":"2014-04-25","open":"1.330","high":"1.351","low":"1.256","close":"1.260","volume":"433316184"},{"day":"2014-04-30","open":"1.255","high":"1.258","low":"1.220","close":"1.254","volume":"521802360"},{"day":"2014-05-09","open":"1.253","high":"1.296","low":"1.220","close":"1.230","volume":"643387004"},{"day":"2014-05-16","open":"1.236","high":"1.264","low":"1.186","close":"1.202","volume":"608345400"},{"day":"2014-05-23","open":"1.195","high":"1.272","low":"1.188","close":"1.270","volume":"691512200"},{"day":"2014-05-30","open":"1.275","high":"1.321","low":"1.272","close":"1.291","volume":"941053232"},{"day":"2014-06-06","open":"1.291","high":"1.335","low":"1.275","close":"1.321","volume":"857733920"},{"day":"2014-06-13","open":"1.315","high":"1.359","low":"1.287","close":"1.350","volume":"903348112"},{"day":"2014-06-20","open":"1.352","high":"1.368","low":"1.281","close":"1.305","volume":"938515904"},{"day":"2014-06-27","open":"1.305","high":"1.368","low":"1.305","close":"1.357","volume":"971020944"},{"day":"2014-07-04","open":"1.357","high":"1.398","low":"1.343","close":"1.381","volume":"778055464"},{"day":"2014-07-11","open":"1.375","high":"1.387","low":"1.321","close":"1.329","volume":"857848896"},{"day":"2014-07-18","open":"1.329","high":"1.338","low":"1.273","close":"1.279","volume":"919058144"},{"day":"2014-07-25","open":"1.280","high":"1.303","low":"1.228","close":"1.257","volume":"1089155920"},{"day":"2014-08-01","open":"1.258","high":"1.318","low":"1.255","close":"1.290","volume":"926236528"},{"day":"2014-08-08","open":"1.285","high":"1.351","low":"1.285","close":"1.347","volume":"1047028336"},{"day":"2014-08-15","open":"1.348","high":"1.371","low":"1.336","close":"1.360","volume":"545607636"},{"day":"2014-08-22","open":"1.360","high":"1.435","low":"1.360","close":"1.429","volume":"735410280"},{"day":"2014-08-29","open":"1.426","high":"1.428","low":"1.365","close":"1.394","volume":"780411560"},{"day":"2014-09-05","open":"1.395","high":"1.466","low":"1.395","close":"1.460","volume":"607917144"},{"day":"2014-09-12","open":"1.453","high":"1.493","low":"1.438","close":"1.483","volume":"611271296"},{"day":"2014-09-19","open":"1.478","high":"1.490","low":"1.418","close":"1.460","volume":"715371040"},{"day":"2014-09-26","open":"1.452","high":"1.486","low":"1.440","close":"1.472","volume":"426811744"},{"day":"2014-09-30","open":"1.472","high":"1.501","low":"1.472","close":"1.500","volume":"127383312"},{"day":"2014-10-10","open":"1.501","high":"1.524","low":"1.493","close":"1.512","volume":"255212792"},{"day":"2014-10-17","open":"1.502","high":"1.521","low":"1.441","close":"1.470","volume":"582898512"},{"day":"2014-10-24","open":"1.465","high":"1.497","low":"1.433","close":"1.441","volume":"441386680"},{"day":"2014-10-31","open":"1.438","high":"1.497","low":"1.429","close":"1.473","volume":"397929776"},{"day":"2014-11-07","open":"1.475","high":"1.503","low":"1.464","close":"1.477","volume":"669862544"},{"day":"2014-11-14","open":"1.480","high":"1.483","low":"1.395","close":"1.406","volume":"655545088"},{"day":"2014-11-21","open":"1.401","high":"1.469","low":"1.398","close":"1.462","volume":"870296192"},{"day":"2014-11-28","open":"1.483","high":"1.537","low":"1.452","close":"1.524","volume":"566225984"},{"day":"2014-12-05","open":"1.520","high":"1.586","low":"1.486","close":"1.529","volume":"1046268976"},{"day":"2014-12-12","open":"1.522","high":"1.577","low":"1.455","close":"1.569","volume":"1001073072"},{"day":"2014-12-19","open":"1.572","high":"1.617","low":"1.518","close":"1.541","volume":"1017387968"},{"day":"2014-12-26","open":"1.534","high":"1.534","low":"1.445","close":"1.488","volume":"857591552"},{"day":"2014-12-31","open":"1.489","high":"1.489","low":"1.411","close":"1.430","volume":"351770104"},{"day":"2015-01-09","open":"1.424","high":"1.536","low":"1.393","close":"1.503","volume":"2097927328"},{"day":"2015-01-16","open":"1.495","high":"1.596","low":"1.475","close":"1.592","volume":"1132233792"},{"day":"2015-01-23","open":"1.576","high":"1.686","low":"1.548","close":"1.638","volume":"2160030064"},{"day":"2015-01-30","open":"1.639","high":"1.700","low":"1.614","close":"1.623","volume":"1087240976"},{"day":"2015-02-06","open":"1.609","high":"1.746","low":"1.604","close":"1.661","volume":"1295373232"},{"day":"2015-02-13","open":"1.661","high":"1.763","low":"1.638","close":"1.761","volume":"1181098448"},{"day":"2015-02-17","open":"1.767","high":"1.839","low":"1.766","close":"1.820","volume":"508595296"},{"day":"2015-02-27","open":"1.825","high":"1.863","low":"1.780","close":"1.863","volume":"816928240"},{"day":"2015-03-06","open":"1.868","high":"1.958","low":"1.863","close":"1.880","volume":"1830610624"},{"day":"2015-03-13","open":"1.855","high":"1.996","low":"1.855","close":"1.992","volume":"1917812032"},{"day":"2015-03-20","open":"2.005","high":"2.145","low":"2.001","close":"2.126","volume":"2091687168"},{"day":"2015-03-27","open":"2.130","high":"2.311","low":"2.126","close":"2.228","volume":"2963079328"},{"day":"2015-04-03","open":"2.210","high":"2.406","low":"2.165","close":"2.391","volume":"2635234912"},{"day":"2015-04-10","open":"2.402","high":"2.480","low":"2.240","close":"2.424","volume":"2205030688"},{"day":"2015-04-17","open":"2.435","high":"2.476","low":"2.304","close":"2.368","volume":"2232791680"},{"day":"2015-04-24","open":"2.355","high":"2.652","low":"2.305","close":"2.645","volume":"2347397888"},{"day":"2015-04-30","open":"2.670","high":"2.810","low":"2.555","close":"2.748","volume":"1971512768"},{"day":"2015-05-08","open":"2.758","high":"2.910","low":"2.641","close":"2.894","volume":"3161475840"},{"day":"2015-05-15","open":"2.908","high":"3.147","low":"2.866","close":"3.016","volume":"3811100480"},{"day":"2015-05-22","open":"3.043","high":"3.499","low":"3.043","close":"3.382","volume":"3409187168"},{"day":"2015-05-29","open":"3.271","high":"3.508","low":"3.158","close":"3.384","volume":"4240537728"},{"day":"2015-06-05","open":"3.398","high":"3.845","low":"3.398","close":"3.703","volume":"4631752512"},{"day":"2015-06-12","open":"3.650","high":"3.729","low":"3.418","close":"3.704","volume":"3925158336"},{"day":"2015-06-19","open":"3.712","high":"3.725","low":"3.142","close":"3.150","volume":"3977905792"},{"day":"2015-06-26","open":"3.150","high":"3.302","low":"2.727","close":"2.767","volume":"2440768672"},{"day":"2015-07-03","open":"2.760","high":"2.843","low":"2.250","close":"2.457","volume":"3627038592"},{"day":"2015-07-10","open":"2.700","high":"2.700","low":"1.887","close":"2.298","volume":"1480103880"},{"day":"2015-07-17","open":"2.524","high":"2.781","low":"2.261","close":"2.688","volume":"2000436976"},{"day":"2015-07-24","open":"2.670","high":"2.858","low":"2.620","close":"2.740","volume":"3746119616"},{"day":"2015-07-31","open":"2.670","high":"2.759","low":"2.253","close":"2.368","volume":"3323149536"},{"day":"2015-08-07","open":"2.325","high":"2.460","low":"2.221","close":"2.459","volume":"1273139936"},{"day":"2015-08-14","open":"2.475","high":"2.645","low":"2.442","close":"2.525","volume":"1836341312"},{"day":"2015-08-21","open":"2.520","high":"2.585","low":"2.220","close":"2.226","volume":"1845917024"},{"day":"2015-08-28","open":"2.112","high":"2.124","low":"1.702","close":"1.941","volume":"1209224464"},{"day":"2015-09-02","open":"1.901","high":"1.909","low":"1.638","close":"1.690","volume":"545610848"},{"day":"2015-09-11","open":"1.741","high":"1.975","low":"1.723","close":"1.922","volume":"1518717232"},{"day":"2015-09-18","open":"1.926","high":"1.937","low":"1.621","close":"1.825","volume":"1157391072"},{"day":"2015-09-25","open":"1.796","high":"2.004","low":"1.770","close":"1.845","volume":"1338356240"},{"day":"2015-09-30","open":"1.849","high":"1.983","low":"1.810","close":"1.935","volume":"570969952"},{"day":"2015-10-09","open":"2.035","high":"2.121","low":"1.993","close":"2.103","volume":"410151456"},{"day":"2015-10-16","open":"2.113","high":"2.340","low":"2.103","close":"2.329","volume":"1356220240"},{"day":"2015-10-23","open":"2.328","high":"2.437","low":"2.215","close":"2.427","volume":"1715588320"},{"day":"2015-10-30","open":"2.443","high":"2.474","low":"2.296","close":"2.349","volume":"1495514720"},{"day":"2015-11-06","open":"2.273","high":"2.558","low":"2.273","close":"2.548","volume":"1540402816"},{"day":"2015-11-13","open":"2.521","high":"2.688","low":"2.478","close":"2.580","volume":"1425838496"},{"day":"2015-11-20","open":"2.523","high":"2.699","low":"2.511","close":"2.645","volume":"1592369920"},{"day":"2015-11-27","open":"2.628","high":"2.755","low":"2.471","close":"2.496","volume":"1755050784"},{"day":"2015-12-04","open":"2.505","high":"2.585","low":"2.369","close":"2.530","volume":"1814179808"},{"day":"2015-12-11","open":"2.534","high":"2.591","low":"2.493","close":"2.510","volume":"1208803440"},{"day":"2015-12-18","open":"2.489","high":"2.675","low":"2.463","close":"2.668","volume":"1250226048"},{"day":"2015-12-25","open":"2.654","high":"2.679","low":"2.565","close":"2.620","volume":"1125118864"},{"day":"2015-12-31","open":"2.623","high":"2.643","low":"2.539","close":"2.539","volume":"670627264"},{"day":"2016-01-08","open":"2.531","high":"2.538","low":"2.030","close":"2.125","volume":"1453978104"},{"day":"2016-01-15","open":"2.067","high":"2.109","low":"1.885","close":"1.997","volume":"1410128448"},{"day":"2016-01-22","open":"1.966","high":"2.129","low":"1.964","close":"2.042","volume":"1559252768"},{"day":"2016-01-29","open":"2.055","high":"2.070","low":"1.794","close":"1.879","volume":"1568481952"},{"day":"2016-02-05","open":"1.875","high":"2.037","low":"1.850","close":"1.999","volume":"1869718064"},{"day":"2016-02-19","open":"1.933","high":"2.135","low":"1.921","close":"2.106","volume":"2267351488"},{"day":"2016-02-26","open":"2.134","high":"2.145","low":"1.872","close":"1.902","volume":"2665571424"},{"day":"2016-03-04","open":"1.886","high":"1.959","low":"1.736","close":"1.810","volume":"2743730720"},{"day":"2016-03-11","open":"1.840","high":"1.911","low":"1.761","close":"1.834","volume":"2863154432"},{"day":"2016-03-18","open":"1.860","high":"2.095","low":"1.858","close":"2.076","volume":"3886404768"},{"day":"2016-03-25","open":"2.100","high":"2.160","low":"2.067","close":"2.099","volume":"3387803520"},{"day":"2016-04-01","open":"2.117","high":"2.158","low":"2.010","close":"2.097","volume":"2745599648"},{"day":"2016-04-08","open":"2.093","high":"2.205","low":"2.084","close":"2.125","volume":"2226014656"},{"day":"2016-04-15","open":"2.148","high":"2.221","low":"2.129","close":"2.195","volume":"2448561536"},{"day":"2016-04-22","open":"2.176","high":"2.178","low":"1.983","close":"2.038","volume":"2542654048"},{"day":"2016-04-29","open":"2.027","high":"2.068","low":"1.980","close":"2.033","volume":"1485839312"},{"day":"2016-05-06","open":"2.036","high":"2.127","low":"2.018","close":"2.018","volume":"2008818752"},{"day":"2016-05-13","open":"2.002","high":"2.002","low":"1.879","close":"1.920","volume":"1758069975"},{"day":"2016-05-20","open":"1.914","high":"2.002","low":"1.902","close":"1.961","volume":"1777258572"},{"day":"2016-05-27","open":"1.967","high":"2.010","low":"1.920","close":"1.968","volume":"1772517488"},{"day":"2016-06-03","open":"1.964","high":"2.136","low":"1.934","close":"2.109","volume":"2028807241"},{"day":"2016-06-08","open":"2.109","high":"2.119","low":"2.072","close":"2.092","volume":"893433815"},{"day":"2016-06-17","open":"2.065","high":"2.072","low":"1.947","close":"2.034","volume":"2124115056"},{"day":"2016-06-24","open":"2.033","high":"2.070","low":"1.979","close":"2.043","volume":"2172901621"},{"day":"2016-07-01","open":"2.030","high":"2.149","low":"2.025","close":"2.116","volume":"2040661121"},{"day":"2016-07-08","open":"2.103","high":"2.164","low":"2.101","close":"2.145","volume":"1401002768"},{"day":"2016-07-15","open":"2.147","high":"2.201","low":"2.092","close":"2.164","volume":"1624709116"},{"day":"2016-07-22","open":"2.162","high":"2.189","low":"2.136","close":"2.154","volume":"1442295848"},{"day":"2016-07-29","open":"2.147","high":"2.185","low":"2.017","close":"2.031","volume":"1681430320"},{"day":"2016-08-05","open":"2.024","high":"2.044","low":"1.981","close":"2.022","volume":"1119131142"},{"day":"2016-08-12","open":"2.019","high":"2.071","low":"1.996","close":"2.035","volume":"1084960595"},{"day":"2016-08-19","open":"2.035","high":"2.122","low":"2.020","close":"2.112","volume":"1442552670"},{"day":"2016-08-26","open":"2.112","high":"2.119","low":"2.058","close":"2.095","volume":"1118366590"},{"day":"2016-09-02","open":"2.089","high":"2.116","low":"2.068","close":"2.081","volume":"707593817"},{"day":"2016-09-09","open":"2.081","high":"2.135","low":"2.069","close":"2.109","volume":"990306655"},{"day":"2016-09-14","open":"2.075","high":"2.087","low":"2.040","close":"2.051","volume":"641926495"},{"day":"2016-09-23","open":"2.054","high":"2.085","low":"2.054","close":"2.065","volume":"419733845"},{"day":"2016-09-30","open":"2.061","high":"2.070","low":"2.025","close":"2.062","volume":"570952187"},{"day":"2016-10-14","open":"2.071","high":"2.125","low":"2.068","close":"2.104","volume":"569516418"},{"day":"2016-10-21","open":"2.104","high":"2.110","low":"2.068","close":"2.090","volume":"557097139"},{"day":"2016-10-28","open":"2.090","high":"2.117","low":"2.071","close":"2.071","volume":"654768454"},{"day":"2016-11-04","open":"2.070","high":"2.087","low":"2.045","close":"2.056","volume":"770855907"},{"day":"2016-11-11","open":"2.054","high":"2.068","low":"2.012","close":"2.060","volume":"792681891"},{"day":"2016-11-18","open":"2.057","high":"2.118","low":"2.057","close":"2.070","volume":"893245733"},{"day":"2016-11-25","open":"2.065","high":"2.100","low":"2.030","close":"2.076","volume":"935054701"},{"day":"2016-12-02","open":"2.079","high":"2.110","low":"2.055","close":"2.055","volume":"1027402216"},{"day":"2016-12-09","open":"2.045","high":"2.071","low":"2.011","close":"2.013","volume":"718190468"},{"day":"2016-12-16","open":"2.010","high":"2.011","low":"1.873","close":"1.908","volume":"1070067398"},{"day":"2016-12-23","open":"1.907","high":"1.912","low":"1.874","close":"1.874","volume":"362468876"},{"day":"2016-12-30","open":"1.869","high":"1.892","low":"1.848","close":"1.881","volume":"404236606"},{"day":"2017-01-06","open":"1.882","high":"1.909","low":"1.876","close":"1.886","volume":"328363313"},{"day":"2017-01-13","open":"1.883","high":"1.889","low":"1.816","close":"1.820","volume":"423588531"},{"day":"2017-01-20","open":"1.820","high":"1.820","low":"1.711","close":"1.801","volume":"997411603"},{"day":"2017-01-26","open":"1.798","high":"1.818","low":"1.777","close":"1.804","volume":"223941501"},{"day":"2017-02-03","open":"1.806","high":"1.809","low":"1.794","close":"1.802","volume":"41205100"},{"day":"2017-02-10","open":"1.799","high":"1.840","low":"1.796","close":"1.824","volume":"431382366"},{"day":"2017-02-17","open":"1.820","high":"1.842","low":"1.800","close":"1.801","volume":"401968396"},{"day":"2017-02-24","open":"1.804","high":"1.859","low":"1.798","close":"1.859","volume":"532179695"},{"day":"2017-03-03","open":"1.859","high":"1.864","low":"1.829","close":"1.849","volume":"390075952"},{"day":"2017-03-10","open":"1.848","high":"1.896","low":"1.847","close":"1.868","volume":"477177150"},{"day":"2017-03-17","open":"1.864","high":"1.900","low":"1.857","close":"1.862","volume":"495162092"},{"day":"2017-03-24","open":"1.863","high":"1.884","low":"1.850","close":"1.882","volume":"539491477"},{"day":"2017-03-31","open":"1.878","high":"1.885","low":"1.811","close":"1.826","volume":"446743105"},{"day":"2017-04-07","open":"1.831","high":"1.871","low":"1.831","close":"1.865","volume":"170830778"},{"day":"2017-04-14","open":"1.865","high":"1.865","low":"1.808","close":"1.810","volume":"373228842"},{"day":"2017-04-21","open":"1.806","high":"1.809","low":"1.738","close":"1.761","volume":"551678303"},{"day":"2017-04-28","open":"1.759","high":"1.779","low":"1.721","close":"1.777","volume":"484987297"},{"day":"2017-05-05","open":"1.775","high":"1.781","low":"1.743","close":"1.743","volume":"365111120"},{"day":"2017-05-12","open":"1.735","high":"1.750","low":"1.657","close":"1.698","volume":"1127863837"},{"day":"2017-05-19","open":"1.701","high":"1.759","low":"1.690","close":"1.725","volume":"671690749"},{"day":"2017-05-26","open":"1.723","high":"1.738","low":"1.658","close":"1.689","volume":"1292244180"},{"day":"2017-06-02","open":"1.719","high":"1.719","low":"1.643","close":"1.678","volume":"836015176"},{"day":"2017-06-09","open":"1.681","high":"1.733","low":"1.680","close":"1.725","volume":"1001970645"},{"day":"2017-06-16","open":"1.715","high":"1.753","low":"1.699","close":"1.739","volume":"979350249"},{"day":"2017-06-23","open":"1.737","high":"1.763","low":"1.706","close":"1.737","volume":"699419290"},{"day":"2017-06-30","open":"1.734","high":"1.758","low":"1.725","close":"1.748","volume":"614558198"},{"day":"2017-07-07","open":"1.747","high":"1.766","low":"1.743","close":"1.750","volume":"588246719"},{"day":"2017-07-14","open":"1.745","high":"1.745","low":"1.661","close":"1.662","volume":"806363096"},{"day":"2017-07-21","open":"1.647","high":"1.648","low":"1.554","close":"1.591","volume":"977135824"},{"day":"2017-07-28","open":"1.589","high":"1.665","low":"1.582","close":"1.647","volume":"730093118"},{"day":"2017-08-04","open":"1.645","high":"1.672","low":"1.630","close":"1.636","volume":"660343157"},{"day":"2017-08-11","open":"1.636","high":"1.690","low":"1.635","close":"1.659","volume":"749031572"},{"day":"2017-08-18","open":"1.664","high":"1.753","low":"1.662","close":"1.733","volume":"973975664"},{"day":"2017-08-25","open":"1.737","high":"1.743","low":"1.702","close":"1.723","volume":"639242681"},{"day":"2017-09-01","open":"1.729","high":"1.780","low":"1.727","close":"1.776","volume":"864875463"},{"day":"2017-09-08","open":"1.773","high":"1.828","low":"1.769","close":"1.791","volume":"749283638"},{"day":"2017-09-15","open":"1.790","high":"1.815","low":"1.780","close":"1.782","volume":"495247506"},{"day":"2017-09-22","open":"1.782","high":"1.811","low":"1.762","close":"1.773","volume":"489833305"},{"day":"2017-09-29","open":"1.770","high":"1.780","low":"1.734","close":"1.780","volume":"389044680"},{"day":"2017-10-13","open":"1.797","high":"1.840","low":"1.790","close":"1.840","volume":"530808047"},{"day":"2017-10-20","open":"1.840","high":"1.840","low":"1.767","close":"1.794","volume":"553593335"},{"day":"2017-10-27","open":"1.791","high":"1.826","low":"1.788","close":"1.801","volume":"438612920"},{"day":"2017-11-03","open":"1.801","high":"1.807","low":"1.726","close":"1.732","volume":"559289862"},{"day":"2017-11-10","open":"1.732","high":"1.800","low":"1.719","close":"1.800","volume":"422895154"},{"day":"2017-11-17","open":"1.799","high":"1.808","low":"1.722","close":"1.723","volume":"471595835"},{"day":"2017-11-24","open":"1.719","high":"1.762","low":"1.678","close":"1.678","volume":"591559528"},{"day":"2017-12-01","open":"1.671","high":"1.695","low":"1.657","close":"1.687","volume":"532727204"},{"day":"2017-12-08","open":"1.683","high":"1.692","low":"1.631","close":"1.675","volume":"750719540"},{"day":"2017-12-15","open":"1.682","high":"1.699","low":"1.666","close":"1.673","volume":"436797429"},{"day":"2017-12-22","open":"1.673","high":"1.688","low":"1.647","close":"1.663","volume":"389614983"},{"day":"2017-12-29","open":"1.662","high":"1.663","low":"1.626","close":"1.644","volume":"489736691"},{"day":"2018-01-05","open":"1.650","high":"1.700","low":"1.646","close":"1.696","volume":"471139597"},{"day":"2018-01-12","open":"1.694","high":"1.707","low":"1.675","close":"1.685","volume":"427239471"},{"day":"2018-01-19","open":"1.680","high":"1.681","low":"1.601","close":"1.630","volume":"1054626841"},{"day":"2018-01-26","open":"1.623","high":"1.751","low":"1.616","close":"1.720","volume":"2147473791"},{"day":"2018-02-02","open":"1.720","high":"1.725","low":"1.582","close":"1.607","volume":"2490761289"},{"day":"2018-02-09","open":"1.586","high":"1.601","low":"1.480","close":"1.502","volume":"2573907145"},{"day":"2018-02-14","open":"1.515","high":"1.574","low":"1.510","close":"1.549","volume":"1028934823"},{"day":"2018-02-23","open":"1.563","high":"1.584","low":"1.554","close":"1.572","volume":"491082744"},{"day":"2018-03-02","open":"1.585","high":"1.699","low":"1.575","close":"1.669","volume":"2219534100"},{"day":"2018-03-09","open":"1.678","high":"1.755","low":"1.665","close":"1.755","volume":"1869423224"},{"day":"2018-03-16","open":"1.773","high":"1.795","low":"1.707","close":"1.716","volume":"2602092419"},{"day":"2018-03-23","open":"1.712","high":"1.768","low":"1.610","close":"1.622","volume":"2869292012"},{"day":"2018-03-30","open":"1.609","high":"1.791","low":"1.595","close":"1.791","volume":"3644082478"},{"day":"2018-04-04","open":"1.805","high":"1.810","low":"1.732","close":"1.732","volume":"1954302917"},{"day":"2018-04-13","open":"1.732","high":"1.757","low":"1.710","close":"1.721","volume":"2383691168"},{"day":"2018-04-20","open":"1.722","high":"1.748","low":"1.659","close":"1.684","volume":"3404398346"},{"day":"2018-04-27","open":"1.684","high":"1.724","low":"1.631","close":"1.707","volume":"2601430867"},{"day":"2018-05-04","open":"1.711","high":"1.729","low":"1.668","close":"1.712","volume":"1565899642"},{"day":"2018-05-11","open":"1.717","high":"1.765","low":"1.715","close":"1.734","volume":"2139928421"},{"day":"2018-05-18","open":"1.732","high":"1.758","low":"1.712","close":"1.731","volume":"1898247067"},{"day":"2018-05-25","open":"1.742","high":"1.772","low":"1.704","close":"1.705","volume":"2123576852"},{"day":"2018-06-01","open":"1.702","high":"1.716","low":"1.609","close":"1.620","volume":"2351595456"},{"day":"2018-06-08","open":"1.624","high":"1.657","low":"1.602","close":"1.620","volume":"1911801574"},{"day":"2018-06-15","open":"1.617","high":"1.624","low":"1.550","close":"1.554","volume":"2201362651"},{"day":"2018-06-22","open":"1.535","high":"1.540","low":"1.427","close":"1.466","volume":"2817199892"},{"day":"2018-06-29","open":"1.479","high":"1.527","low":"1.437","close":"1.524","volume":"2746657853"},{"day":"2018-07-06","open":"1.522","high":"1.531","low":"1.443","close":"1.464","volume":"3135301544"},{"day":"2018-07-13","open":"1.474","high":"1.548","low":"1.468","close":"1.542","volume":"3070238283"},{"day":"2018-07-20","open":"1.536","high":"1.557","low":"1.505","close":"1.535","volume":"2011737165"},{"day":"2018-07-27","open":"1.534","high":"1.567","low":"1.515","close":"1.518","volume":"2407720881"},{"day":"2018-08-03","open":"1.514","high":"1.520","low":"1.411","close":"1.414","volume":"3046904811"},{"day":"2018-08-10","open":"1.405","high":"1.441","low":"1.368","close":"1.437","volume":"4384565765"},{"day":"2018-08-17","open":"1.422","high":"1.460","low":"1.366","close":"1.369","volume":"3589661023"},{"day":"2018-08-24","open":"1.363","high":"1.395","low":"1.340","close":"1.382","volume":"3315971443"},{"day":"2018-08-31","open":"1.387","high":"1.429","low":"1.366","close":"1.369","volume":"2694452418"},{"day":"2018-09-07","open":"1.364","high":"1.394","low":"1.350","close":"1.360","volume":"3331651368"},{"day":"2018-09-14","open":"1.353","high":"1.360","low":"1.304","close":"1.304","volume":"4036286760"},{"day":"2018-09-21","open":"1.296","high":"1.346","low":"1.282","close":"1.343","volume":"3705798502"},{"day":"2018-09-28","open":"1.333","high":"1.361","low":"1.327","close":"1.346","volume":"2501790582"},{"day":"2018-10-12","open":"1.317","high":"1.322","low":"1.173","close":"1.206","volume":"4036646336"},{"day":"2018-10-19","open":"1.205","high":"1.220","low":"1.136","close":"1.189","volume":"5423431839"},{"day":"2018-10-26","open":"1.220","high":"1.268","low":"1.183","close":"1.203","volume":"5966746675"},{"day":"2018-11-02","open":"1.205","high":"1.292","low":"1.168","close":"1.291","volume":"6451666199"},{"day":"2018-11-09","open":"1.284","high":"1.308","low":"1.252","close":"1.260","volume":"4887186079"},{"day":"2018-11-16","open":"1.258","high":"1.345","low":"1.256","close":"1.332","volume":"5302339885"},{"day":"2018-11-23","open":"1.328","high":"1.332","low":"1.244","close":"1.248","volume":"4250515717"},{"day":"2018-11-30","open":"1.247","high":"1.287","low":"1.234","close":"1.264","volume":"2995776927"},{"day":"2018-12-07","open":"1.301","high":"1.326","low":"1.273","close":"1.275","volume":"3301474672"},{"day":"2018-12-14","open":"1.269","high":"1.295","low":"1.247","close":"1.248","volume":"2643247031"},{"day":"2018-12-21","open":"1.242","high":"1.248","low":"1.203","close":"1.213","volume":"3481115010"},{"day":"2018-12-28","open":"1.212","high":"1.232","low":"1.186","close":"1.194","volume":"3339211668"},{"day":"2019-01-04","open":"1.198","high":"1.199","low":"1.152","close":"1.195","volume":"2462612300"},{"day":"2019-01-11","open":"1.197","high":"1.232","low":"1.193","close":"1.209","volume":"3041824434"},{"day":"2019-01-18","open":"1.210","high":"1.224","low":"1.189","close":"1.216","volume":"2916664083"},{"day":"2019-01-25","open":"1.218","high":"1.231","low":"1.194","close":"1.214","volume":"2868737727"},{"day":"2019-02-01","open":"1.220","high":"1.227","low":"1.172","close":"1.221","volume":"3553072774"},{"day":"2019-02-15","open":"1.223","high":"1.314","low":"1.223","close":"1.302","volume":"4270686780"},{"day":"2019-02-22","open":"1.310","high":"1.406","low":"1.308","close":"1.406","volume":"4910620686"},{"day":"2019-03-01","open":"1.432","high":"1.519","low":"1.416","close":"1.500","volume":"5538855338"},{"day":"2019-03-08","open":"1.526","high":"1.648","low":"1.525","close":"1.584","volume":"7228246832"},{"day":"2019-03-15","open":"1.600","high":"1.715","low":"1.556","close":"1.589","volume":"9310549827"},{"day":"2019-03-22","open":"1.598","high":"1.655","low":"1.581","close":"1.621","volume":"5695851391"},{"day":"2019-03-29","open":"1.594","high":"1.627","low":"1.546","close":"1.624","volume":"4316961282"},{"day":"2019-04-04","open":"1.635","high":"1.710","low":"1.635","close":"1.701","volume":"3289086756"},{"day":"2019-04-12","open":"1.709","high":"1.716","low":"1.611","close":"1.624","volume":"3431905606"},{"day":"2019-04-19","open":"1.647","high":"1.655","low":"1.568","close":"1.645","volume":"3292461709"},{"day":"2019-04-26","open":"1.645","high":"1.649","low":"1.584","close":"1.589","volume":"3243706154"},{"day":"2019-04-30","open":"1.589","high":"1.594","low":"1.540","close":"1.553","volume":"1437468701"},{"day":"2019-05-10","open":"1.496","high":"1.497","low":"1.402","close":"1.465","volume":"5665148587"},{"day":"2019-05-17","open":"1.448","high":"1.472","low":"1.411","close":"1.416","volume":"3206224638"},{"day":"2019-05-24","open":"1.412","high":"1.441","low":"1.377","close":"1.384","volume":"3237549758"},{"day":"2019-05-31","open":"1.387","high":"1.445","low":"1.383","close":"1.425","volume":"3163293350"},{"day":"2019-06-06","open":"1.428","high":"1.438","low":"1.355","close":"1.363","volume":"2333575624"},{"day":"2019-06-14","open":"1.364","high":"1.432","low":"1.356","close":"1.397","volume":"3354069686"},{"day":"2019-06-21","open":"1.395","high":"1.494","low":"1.383","close":"1.473","volume":"4604784185"},{"day":"2019-06-28","open":"1.467","high":"1.473","low":"1.426","close":"1.457","volume":"3153323153"},{"day":"2019-07-05","open":"1.487","high":"1.518","low":"1.469","close":"1.492","volume":"2795676125"},{"day":"2019-07-12","open":"1.488","high":"1.488","low":"1.439","close":"1.465","volume":"1903920452"},{"day":"2019-07-19","open":"1.458","high":"1.505","low":"1.441","close":"1.486","volume":"2846761949"},{"day":"2019-07-26","open":"1.488","high":"1.511","low":"1.453","close":"1.506","volume":"2083435962"},{"day":"2019-08-02","open":"1.504","high":"1.536","low":"1.481","close":"1.501","volume":"2100800836"},{"day":"2019-08-09","open":"1.495","high":"1.509","low":"1.423","close":"1.450","volume":"2160217167"},{"day":"2019-08-16","open":"1.457","high":"1.527","low":"1.451","close":"1.512","volume":"2135529077"},{"day":"2019-08-23","open":"1.528","high":"1.573","low":"1.524","close":"1.555","volume":"2563798192"},{"day":"2019-08-30","open":"1.540","high":"1.586","low":"1.529","close":"1.549","volume":"2418299414"},{"day":"2019-09-06","open":"1.550","high":"1.647","low":"1.550","close":"1.631","volume":"2155968482"},{"day":"2019-09-12","open":"1.639","high":"1.672","low":"1.628","close":"1.646","volume":"1738781272"},{"day":"2019-09-20","open":"1.649","high":"1.658","low":"1.607","close":"1.638","volume":"2047281038"},{"day":"2019-09-27","open":"1.635","high":"1.642","low":"1.560","close":"1.587","volume":"2097843847"},{"day":"2019-09-30","open":"1.585","high":"1.590","low":"1.565","close":"1.570","volume":"276484650"},{"day":"2019-10-11","open":"1.571","high":"1.615","low":"1.543","close":"1.606","volume":"1694982938"},{"day":"2019-10-18","open":"1.615","high":"1.630","low":"1.582","close":"1.589","volume":"1654070374"},{"day":"2019-10-25","open":"1.588","high":"1.616","low":"1.570","close":"1.616","volume":"1699586633"},{"day":"2019-11-01","open":"1.630","high":"1.646","low":"1.602","close":"1.625","volume":"1625383652"},{"day":"2019-11-08","open":"1.624","high":"1.666","low":"1.624","close":"1.645","volume":"1619354750"},{"day":"2019-11-15","open":"1.641","high":"1.641","low":"1.593","close":"1.614","volume":"1209941491"},{"day":"2019-11-22","open":"1.613","high":"1.679","low":"1.603","close":"1.614","volume":"1804904352"},{"day":"2019-11-29","open":"1.616","high":"1.622","low":"1.585","close":"1.600","volume":"1349740176"},{"day":"2019-12-06","open":"1.605","high":"1.662","low":"1.586","close":"1.662","volume":"1378171520"},{"day":"2019-12-13","open":"1.667","high":"1.695","low":"1.645","close":"1.693","volume":"1404972776"},{"day":"2019-12-20","open":"1.693","high":"1.741","low":"1.686","close":"1.708","volume":"1616789909"},{"day":"2019-12-27","open":"1.703","high":"1.737","low":"1.667","close":"1.698","volume":"1477058386"},{"day":"2020-01-03","open":"1.695","high":"1.774","low":"1.684","close":"1.764","volume":"1187236488"},{"day":"2020-01-10","open":"1.756","high":"1.847","low":"1.753","close":"1.831","volume":"2109382972"},{"day":"2020-01-17","open":"1.834","high":"1.874","low":"1.820","close":"1.858","volume":"1652963302"},{"day":"2020-01-23","open":"1.862","high":"1.930","low":"1.829","close":"1.853","volume":"2091106574"},{"day":"2020-02-07","open":"1.670","high":"1.949","low":"1.669","close":"1.940","volume":"3549260614"},{"day":"2020-02-14","open":"1.938","high":"2.022","low":"1.924","close":"1.987","volume":"1874318233"},{"day":"2020-02-21","open":"2.005","high":"2.162","low":"2.004","close":"2.145","volume":"3064951376"},{"day":"2020-02-28","open":"2.137","high":"2.210","low":"1.985","close":"1.995","volume":"3768915275"},{"day":"2020-03-06","open":"2.026","high":"2.155","low":"1.999","close":"2.111","volume":"2674813701"},{"day":"2020-03-13","open":"2.068","high":"2.090","low":"1.850","close":"1.952","volume":"2748381822"},{"day":"2020-03-20","open":"1.953","high":"1.960","low":"1.768","close":"1.847","volume":"4139467552"},{"day":"2020-03-27","open":"1.790","high":"1.882","low":"1.748","close":"1.830","volume":"3534556721"},{"day":"2020-04-03","open":"1.807","high":"1.854","low":"1.762","close":"1.834","volume":"2493392951"},{"day":"2020-04-10","open":"1.871","high":"1.925","low":"1.866","close":"1.877","volume":"1852430694"},{"day":"2020-04-17","open":"1.872","high":"1.969","low":"1.840","close":"1.943","volume":"1992840717"},{"day":"2020-04-24","open":"1.945","high":"1.978","low":"1.920","close":"1.930","volume":"1438290378"},{"day":"2020-04-30","open":"1.938","high":"1.999","low":"1.890","close":"1.993","volume":"1546815939"},{"day":"2020-05-08","open":"1.980","high":"2.058","low":"1.974","close":"2.042","volume":"938043099"},{"day":"2020-05-15","open":"2.054","high":"2.063","low":"2.010","close":"2.042","volume":"1344016667"},{"day":"2020-05-22","open":"2.045","high":"2.074","low":"1.960","close":"1.972","volume":"1651852542"},{"day":"2020-05-29","open":"1.968","high":"2.038","low":"1.948","close":"2.006","volume":"1842803639"},{"day":"2020-06-05","open":"2.024","high":"2.087","low":"2.020","close":"2.087","volume":"1431470592"},{"day":"2020-06-12","open":"2.101","high":"2.161","low":"2.068","close":"2.141","volume":"1515433276"},{"day":"2020-06-19","open":"2.143","high":"2.253","low":"2.140","close":"2.238","volume":"1721758965"},{"day":"2020-06-24","open":"2.246","high":"2.318","low":"2.245","close":"2.307","volume":"893428644"},{"day":"2020-07-03","open":"2.292","high":"2.390","low":"2.280","close":"2.380","volume":"1720175485"},{"day":"2020-07-10","open":"2.384","high":"2.706","low":"2.375","close":"2.685","volume":"2299586143"},{"day":"2020-07-17","open":"2.693","high":"2.810","low":"2.529","close":"2.583","volume":"4211272008"},{"day":"2020-07-24","open":"2.620","high":"2.713","low":"2.525","close":"2.537","volume":"3278890401"},{"day":"2020-07-31","open":"2.544","high":"2.724","low":"2.513","close":"2.708","volume":"2245187011"},{"day":"2020-08-07","open":"2.734","high":"2.794","low":"2.610","close":"2.657","volume":"2053505204"},{"day":"2020-08-14","open":"2.641","high":"2.680","low":"2.492","close":"2.579","volume":"2224643546"},{"day":"2020-08-21","open":"2.591","high":"2.631","low":"2.272","close":"2.546","volume":"1905736861"},{"day":"2020-08-28","open":"2.563","high":"2.670","low":"2.503","close":"2.666","volume":"2064643910"},{"day":"2020-09-04","open":"2.676","high":"2.696","low":"2.596","close":"2.638","volume":"1596903882"},{"day":"2020-09-11","open":"2.628","high":"2.650","low":"2.390","close":"2.449","volume":"1942695658"},{"day":"2020-09-18","open":"2.476","high":"2.515","low":"2.437","close":"2.513","volume":"1267002423"},{"day":"2020-09-25","open":"2.516","high":"2.520","low":"2.444","close":"2.457","volume":"1103132414"},{"day":"2020-09-30","open":"2.465","high":"2.513","low":"2.432","close":"2.489","volume":"593759889"},{"day":"2020-10-09","open":"2.539","high":"2.586","low":"2.534","close":"2.581","volume":"244202537"},{"day":"2020-10-16","open":"2.606","high":"2.697","low":"2.601","close":"2.634","volume":"1236842416"},{"day":"2020-10-23","open":"2.648","high":"2.656","low":"2.504","close":"2.516","volume":"1411761805"},{"day":"2020-10-30","open":"2.500","high":"2.619","low":"2.468","close":"2.563","volume":"1366086104"},{"day":"2020-11-06","open":"2.570","high":"2.697","low":"2.570","close":"2.637","volume":"1275617599"},{"day":"2020-11-13","open":"2.653","high":"2.736","low":"2.590","close":"2.619","volume":"1533945507"},{"day":"2020-11-20","open":"2.626","high":"2.627","low":"2.506","close":"2.576","volume":"1746527900"},{"day":"2020-11-27","open":"2.579","high":"2.612","low":"2.498","close":"2.532","volume":"1398146896"},{"day":"2020-12-04","open":"2.532","high":"2.640","low":"2.506","close":"2.637","volume":"1588096963"},{"day":"2020-12-11","open":"2.625","high":"2.665","low":"2.575","close":"2.601","volume":"1124729397"},{"day":"2020-12-18","open":"2.600","high":"2.706","low":"2.585","close":"2.688","volume":"1009922034"},{"day":"2020-12-25","open":"2.687","high":"2.792","low":"2.686","close":"2.749","volume":"1935291269"},{"day":"2020-12-31","open":"2.748","high":"2.869","low":"2.702","close":"2.866","volume":"921031887"},{"day":"2021-01-08","open":"2.864","high":"3.086","low":"2.861","close":"3.036","volume":"1113062678"},{"day":"2021-01-15","open":"3.052","high":"3.094","low":"2.919","close":"2.990","volume":"1113300183"},{"day":"2021-01-22","open":"2.969","high":"3.252","low":"2.949","close":"3.241","volume":"1224858551"},{"day":"2021-01-29","open":"3.242","high":"3.307","low":"2.966","close":"3.029","volume":"1370234762"},{"day":"2021-02-05","open":"3.024","high":"3.160","low":"3.001","close":"3.084","volume":"1097718133"},{"day":"2021-02-10","open":"3.171","high":"3.309","low":"3.163","close":"3.293","volume":"476706547"},{"day":"2021-02-19","open":"3.353","high":"3.359","low":"3.086","close":"3.170","volume":"694373497"},{"day":"2021-02-26","open":"3.156","high":"3.159","low":"2.790","close":"2.814","volume":"2575841929"},{"day":"2021-03-05","open":"2.850","high":"2.915","low":"2.705","close":"2.772","volume":"2443132361"},{"day":"2021-03-12","open":"2.783","high":"2.803","low":"2.520","close":"2.658","volume":"3084518565"},{"day":"2021-03-19","open":"2.640","high":"2.661","low":"2.523","close":"2.579","volume":"1856616339"},{"day":"2021-03-26","open":"2.583","high":"2.658","low":"2.515","close":"2.650","volume":"1783645124"},{"day":"2021-04-02","open":"2.644","high":"2.769","low":"2.621","close":"2.756","volume":"1343577225"},{"day":"2021-04-09","open":"2.762","high":"2.769","low":"2.677","close":"2.690","volume":"824397571"},{"day":"2021-04-16","open":"2.683","high":"2.715","low":"2.618","close":"2.688","volume":"1288405280"},{"day":"2021-04-23","open":"2.681","high":"2.905","low":"2.672","close":"2.891","volume":"1435464129"},{"day":"2021-04-30","open":"2.910","high":"3.004","low":"2.846","close":"2.989","volume":"1331274940"},{"day":"2021-05-07","open":"2.963","high":"2.963","low":"2.816","close":"2.819","volume":"567525135"},{"day":"2021-05-14","open":"2.820","high":"2.938","low":"2.769","close":"2.937","volume":"1221904013"},{"day":"2021-05-21","open":"2.945","high":"3.065","low":"2.945","close":"3.012","volume":"1063955411"},{"day":"2021-05-28","open":"3.010","high":"3.175","low":"2.972","close":"3.121","volume":"1070146828"},{"day":"2021-06-04","open":"3.130","high":"3.202","low":"3.077","close":"3.141","volume":"913647856"},{"day":"2021-06-11","open":"3.136","high":"3.212","low":"3.079","close":"3.195","volume":"907088442"},{"day":"2021-06-18","open":"3.191","high":"3.199","low":"3.021","close":"3.137","volume":"966889455"},{"day":"2021-06-25","open":"3.127","high":"3.254","low":"3.100","close":"3.243","volume":"968728449"},{"day":"2021-07-02","open":"3.238","high":"3.388","low":"3.224","close":"3.227","volume":"1069679125"},{"day":"2021-07-09","open":"3.223","high":"3.360","low":"3.142","close":"3.303","volume":"1172436253"},{"day":"2021-07-16","open":"3.339","high":"3.452","low":"3.315","close":"3.328","volume":"940577232"},{"day":"2021-07-23","open":"3.326","high":"3.463","low":"3.311","close":"3.367","volume":"893690199"},{"day":"2021-07-30","open":"3.340","high":"3.371","low":"3.063","close":"3.328","volume":"1456926194"},{"day":"2021-08-06","open":"3.328","high":"3.457","low":"3.290","close":"3.386","volume":"947723347"},{"day":"2021-08-13","open":"3.351","high":"3.366","low":"3.228","close":"3.249","volume":"976122263"},{"day":"2021-08-20","open":"3.225","high":"3.244","low":"3.067","close":"3.100","volume":"1204076395"},{"day":"2021-08-27","open":"3.105","high":"3.261","low":"3.102","close":"3.158","volume":"888599111"},{"day":"2021-09-03","open":"3.170","high":"3.214","low":"2.996","close":"3.010","volume":"997111245"},{"day":"2021-09-10","open":"3.012","high":"3.180","low":"2.993","close":"3.135","volume":"928239347"},{"day":"2021-09-17","open":"3.127","high":"3.174","low":"3.026","close":"3.097","volume":"791869344"},{"day":"2021-09-24","open":"3.057","high":"3.147","low":"3.051","close":"3.109","volume":"479126260"},{"day":"2021-09-30","open":"3.119","high":"3.177","low":"3.067","close":"3.148","volume":"601207060"},{"day":"2021-10-08","open":"3.169","high":"3.186","low":"3.125","close":"3.138","volume":"146534774"},{"day":"2021-10-15","open":"3.147","high":"3.180","low":"3.013","close":"3.176","volume":"765279966"},{"day":"2021-10-22","open":"3.178","high":"3.215","low":"3.128","close":"3.185","volume":"564180376"},{"day":"2021-10-29","open":"3.182","high":"3.262","low":"3.151","close":"3.249","volume":"605122198"},{"day":"2021-11-05","open":"3.245","high":"3.276","low":"3.198","close":"3.248","volume":"584869171"},{"day":"2021-11-12","open":"3.240","high":"3.335","low":"3.234","close":"3.324","volume":"532667687"},{"day":"2021-11-19","open":"3.324","high":"3.329","low":"3.268","close":"3.313","volume":"551614229"},{"day":"2021-11-26","open":"3.322","high":"3.402","low":"3.314","close":"3.364","volume":"492676184"},{"day":"2021-12-03","open":"3.345","high":"3.411","low":"3.338","close":"3.370","volume":"521336430"},{"day":"2021-12-10","open":"3.354","high":"3.377","low":"3.235","close":"3.370","volume":"591807201"},{"day":"2021-12-17","open":"3.362","high":"3.411","low":"3.320","close":"3.328","volume":"427976185"},{"day":"2021-12-24","open":"3.322","high":"3.328","low":"3.181","close":"3.196","volume":"629708981"},{"day":"2021-12-31","open":"3.183","high":"3.247","low":"3.173","close":"3.218","volume":"694259081"},{"day":"2022-01-07","open":"3.236","high":"3.242","low":"2.998","close":"3.003","volume":"1112900414"},{"day":"2022-01-14","open":"3.000","high":"3.043","low":"2.956","close":"3.015","volume":"1268594331"},{"day":"2022-01-21","open":"3.000","high":"3.075","low":"2.927","close":"2.941","volume":"1115749024"},{"day":"2022-01-28","open":"2.929","high":"2.972","low":"2.794","close":"2.819","volume":"1461640849"},{"day":"2022-02-11","open":"2.870","high":"2.891","low":"2.655","close":"2.660","volume":"1793414423"},{"day":"2022-02-18","open":"2.648","high":"2.768","low":"2.626","close":"2.739","volume":"1762114183"},{"day":"2022-02-25","open":"2.739","high":"2.790","low":"2.656","close":"2.763","volume":"1868275317"},{"day":"2022-03-04","open":"2.763","high":"2.814","low":"2.652","close":"2.662","volume":"1695753302"},{"day":"2022-03-11","open":"2.641","high":"2.642","low":"2.388","close":"2.583","volume":"3992522651"},{"day":"2022-03-18","open":"2.547","high":"2.674","low":"2.400","close":"2.635","volume":"3728420304"},{"day":"2022-03-25","open":"2.639","high":"2.666","low":"2.559","close":"2.565","volume":"2050673185"},{"day":"2022-04-01","open":"2.540","high":"2.610","low":"2.494","close":"2.580","volume":"2315589061"},{"day":"2022-04-08","open":"2.566","high":"2.577","low":"2.467","close":"2.491","volume":"1142961870"},{"day":"2022-04-15","open":"2.460","high":"2.465","low":"2.339","close":"2.385","volume":"2834576599"},{"day":"2022-04-22","open":"2.361","high":"2.430","low":"2.207","close":"2.225","volume":"3044796672"},{"day":"2022-04-29","open":"2.177","high":"2.250","low":"2.057","close":"2.244","volume":"5046498556"},{"day":"2022-05-06","open":"2.200","high":"2.244","low":"2.148","close":"2.177","volume":"1499119425"},{"day":"2022-05-13","open":"2.165","high":"2.323","low":"2.121","close":"2.285","volume":"3294513265"},{"day":"2022-05-20","open":"2.295","high":"2.352","low":"2.249","close":"2.347","volume":"1876824640"},{"day":"2022-05-27","open":"2.347","high":"2.348","low":"2.212","close":"2.251","volume":"2276329949"},{"day":"2022-06-02","open":"2.262","high":"2.389","low":"2.251","close":"2.386","volume":"1496749538"},{"day":"2022-06-10","open":"2.380","high":"2.498","low":"2.379","close":"2.480","volume":"1820291563"},{"day":"2022-06-17","open":"2.458","high":"2.588","low":"2.388","close":"2.584","volume":"2033462570"},{"day":"2022-06-24","open":"2.590","high":"2.740","low":"2.586","close":"2.738","volume":"1793028961"},{"day":"2022-07-01","open":"2.751","high":"2.780","low":"2.680","close":"2.699","volume":"1830396902"},{"day":"2022-07-08","open":"2.682","high":"2.803","low":"2.663","close":"2.731","volume":"1735558944"},{"day":"2022-07-15","open":"2.729","high":"2.758","low":"2.595","close":"2.680","volume":"1821454790"},{"day":"2022-07-22","open":"2.685","high":"2.732","low":"2.635","close":"2.651","volume":"1338601819"},{"day":"2022-07-29","open":"2.647","high":"2.669","low":"2.588","close":"2.594","volume":"1418507214"},{"day":"2022-08-05","open":"2.580","high":"2.657","low":"2.536","close":"2.606","volume":"1523914995"},{"day":"2022-08-12","open":"2.588","high":"2.647","low":"2.570","close":"2.613","volume":"1140356751"},{"day":"2022-08-19","open":"2.606","high":"2.713","low":"2.606","close":"2.653","volume":"1063863971"},{"day":"2022-08-26","open":"2.650","high":"2.721","low":"2.556","close":"2.566","volume":"1314395136"},{"day":"2022-09-02","open":"2.541","high":"2.564","low":"2.443","close":"2.461","volume":"1422496560"},{"day":"2022-09-09","open":"2.454","high":"2.509","low":"2.420","close":"2.476","volume":"1766570859"},{"day":"2022-09-16","open":"2.485","high":"2.494","low":"2.297","close":"2.297","volume":"1413190932"},{"day":"2022-09-23","open":"2.292","high":"2.327","low":"2.209","close":"2.239","volume":"2179592845"},{"day":"2022-09-30","open":"2.226","high":"2.306","low":"2.219","close":"2.221","volume":"2316293057"},{"day":"2022-10-14","open":"2.219","high":"2.380","low":"2.166","close":"2.365","volume":"2813826690"},{"day":"2022-10-21","open":"2.349","high":"2.397","low":"2.296","close":"2.321","volume":"2353181762"},{"day":"2022-10-28","open":"2.323","high":"2.348","low":"2.179","close":"2.187","volume":"3372154228"},{"day":"2022-11-04","open":"2.166","high":"2.394","low":"2.164","close":"2.383","volume":"3482991628"},{"day":"2022-11-11","open":"2.372","high":"2.400","low":"2.276","close":"2.330","volume":"3313512656"},{"day":"2022-11-18","open":"2.333","high":"2.372","low":"2.281","close":"2.315","volume":"3203765107"},{"day":"2022-11-25","open":"2.298","high":"2.320","low":"2.233","close":"2.242","volume":"2221440543"},{"day":"2022-12-02","open":"2.203","high":"2.339","low":"2.197","close":"2.316","volume":"2638588223"},{"day":"2022-12-09","open":"2.327","high":"2.359","low":"2.298","close":"2.348","volume":"2663256081"},{"day":"2022-12-16","open":"2.342","high":"2.348","low":"2.291","close":"2.298","volume":"1915824202"},{"day":"2022-12-23","open":"2.304","high":"2.317","low":"2.207","close":"2.222","volume":"2038246200"},{"day":"2022-12-30","open":"2.224","high":"2.298","low":"2.222","close":"2.279","volume":"2382758210"},{"day":"2023-01-06","open":"2.267","high":"2.368","low":"2.246","close":"2.350","volume":"1936682582"},{"day":"2023-01-13","open":"2.361","high":"2.417","low":"2.356","close":"2.417","volume":"1715045795"},{"day":"2023-01-20","open":"2.421","high":"2.518","low":"2.417","close":"2.507","volume":"1728711006"},{"day":"2023-02-03","open":"2.577","high":"2.579","low":"2.475","close":"2.500","volume":"2181935893"},{"day":"2023-02-10","open":"2.486","high":"2.496","low":"2.440","close":"2.465","volume":"2113192764"},{"day":"2023-02-17","open":"2.463","high":"2.508","low":"2.375","close":"2.378","volume":"1982557503"},{"day":"2023-02-24","open":"2.372","high":"2.409","low":"2.353","close":"2.357","volume":"2131981818"},{"day":"2023-03-03","open":"2.347","high":"2.378","low":"2.332","close":"2.352","volume":"2691066016"},{"day":"2023-03-10","open":"2.356","high":"2.365","low":"2.284","close":"2.300","volume":"4118442907"},{"day":"2023-03-17","open":"2.295","high":"2.306","low":"2.221","close":"2.228","volume":"6137372152"},{"day":"2023-03-24","open":"2.229","high":"2.300","low":"2.213","close":"2.297","volume":"6366345481"},{"day":"2023-03-31","open":"2.293","high":"2.328","low":"2.290","close":"2.327","volume":"3626769043"},{"day":"2023-04-07","open":"2.327","high":"2.380","low":"2.327","close":"2.369","volume":"3003182680"},{"day":"2023-04-14","open":"2.379","high":"2.386","low":"2.332","close":"2.355","volume":"2843286095"},{"day":"2023-04-21","open":"2.354","high":"2.372","low":"2.268","close":"2.269","volume":"2435982533"},{"day":"2023-04-28","open":"2.267","high":"2.269","low":"2.178","close":"2.255","volume":"4070907977"},{"day":"2023-05-05","open":"2.253","high":"2.253","low":"2.194","close":"2.202","volume":"910362064"},{"day":"2023-05-12","open":"2.210","high":"2.229","low":"2.166","close":"2.185","volume":"4192675276"},{"day":"2023-05-19","open":"2.192","high":"2.244","low":"2.190","close":"2.215","volume":"3153046816"},{"day":"2023-05-26","open":"2.216","high":"2.227","low":"2.153","close":"2.167","volume":"3681040203"},{"day":"2023-06-02","open":"2.171","high":"2.179","low":"2.120","close":"2.175","volume":"3957993103"},{"day":"2023-06-09","open":"2.173","high":"2.173","low":"2.064","close":"2.086","volume":"4515741031"},{"day":"2023-06-16","open":"2.080","high":"2.215","low":"2.076","close":"2.208","volume":"5113746396"},{"day":"2023-06-21","open":"2.211","high":"2.220","low":"2.155","close":"2.156","volume":"2033883946"},{"day":"2023-06-30","open":"2.140","high":"2.174","low":"2.107","close":"2.164","volume":"3321754470"},{"day":"2023-07-07","open":"2.168","high":"2.185","low":"2.116","close":"2.118","volume":"2458952176"},{"day":"2023-07-14","open":"2.127","high":"2.187","low":"2.126","close":"2.169","volume":"2541674895"},{"day":"2023-07-21","open":"2.163","high":"2.164","low":"2.097","close":"2.110","volume":"2881300523"},{"day":"2023-07-28","open":"2.100","high":"2.169","low":"2.088","close":"2.163","volume":"3673778099"},{"day":"2023-08-04","open":"2.172","high":"2.225","low":"2.158","close":"2.204","volume":"2885832668"},{"day":"2023-08-11","open":"2.198","high":"2.201","low":"2.129","close":"2.129","volume":"2709333099"},{"day":"2023-08-18","open":"2.112","high":"2.116","low":"2.061","close":"2.065","volume":"3253476155"},{"day":"2023-08-25","open":"2.061","high":"2.061","low":"1.982","close":"1.991","volume":"4413067982"},{"day":"2023-09-01","open":"2.136","high":"2.136","low":"2.000","close":"2.049","volume":"3865432883"},{"day":"2023-09-08","open":"2.058","high":"2.069","low":"1.987","close":"1.998","volume":"2657637023"},{"day":"2023-09-15","open":"2.000","high":"2.025","low":"1.946","close":"1.954","volume":"3347207021"},{"day":"2023-09-22","open":"1.951","high":"1.982","low":"1.911","close":"1.964","volume":"3544341683"},{"day":"2023-09-28","open":"1.955","high":"1.977","low":"1.935","close":"1.953","volume":"2218868039"},{"day":"2023-10-13","open":"1.950","high":"1.971","low":"1.928","close":"1.945","volume":"2698202455"},{"day":"2023-10-20","open":"1.945","high":"1.947","low":"1.845","close":"1.850","volume":"3216980606"},{"day":"2023-10-27","open":"1.845","high":"1.888","low":"1.793","close":"1.881","volume":"4873204996"},{"day":"2023-11-03","open":"1.874","high":"1.933","low":"1.874","close":"1.918","volume":"3486801254"},{"day":"2023-11-10","open":"1.930","high":"1.983","low":"1.930","close":"1.955","volume":"3546217265"},{"day":"2023-11-17","open":"1.965","high":"1.983","low":"1.918","close":"1.934","volume":"2871679726"},{"day":"2023-11-24","open":"1.934","high":"1.962","low":"1.885","close":"1.888","volume":"3191478652"},{"day":"2023-12-01","open":"1.883","high":"1.890","low":"1.856","close":"1.881","volume":"2412353013"},{"day":"2023-12-08","open":"1.878","high":"1.880","low":"1.816","close":"1.843","volume":"2919343849"},{"day":"2023-12-15","open":"1.836","high":"1.872","low":"1.795","close":"1.802","volume":"1661131497"},{"day":"2023-12-22","open":"1.792","high":"1.801","low":"1.747","close":"1.780","volume":"3920998966"},{"day":"2023-12-29","open":"1.777","high":"1.848","low":"1.750","close":"1.842","volume":"4380374870"},{"day":"2024-01-05","open":"1.842","high":"1.842","low":"1.720","close":"1.728","volume":"3753617708"},{"day":"2024-01-12","open":"1.724","high":"1.744","low":"1.681","close":"1.714","volume":"5987968335"},{"day":"2024-01-19","open":"1.702","high":"1.720","low":"1.635","close":"1.669","volume":"6576431059"},{"day":"2024-01-26","open":"1.663","high":"1.676","low":"1.599","close":"1.637","volume":"7394980242"},{"day":"2024-02-02","open":"1.638","high":"1.643","low":"1.471","close":"1.508","volume":"9683171204"},{"day":"2024-02-08","open":"1.491","high":"1.718","low":"1.444","close":"1.681","volume":"16895127991"},{"day":"2024-02-23","open":"1.704","high":"1.736","low":"1.675","close":"1.709","volume":"6652700542"},{"day":"2024-03-01","open":"1.706","high":"1.781","low":"1.690","close":"1.775","volume":"7023954674"},{"day":"2024-03-08","open":"1.773","high":"1.805","low":"1.730","close":"1.756","volume":"7952066119"},{"day":"2024-03-15","open":"1.760","high":"1.863","low":"1.760","close":"1.833","volume":"5924677355"},{"day":"2024-03-22","open":"1.850","high":"1.875","low":"1.808","close":"1.817","volume":"4606215599"},{"day":"2024-03-29","open":"1.809","high":"1.819","low":"1.738","close":"1.768","volume":"4270333774"},{"day":"2024-04-03","open":"1.780","high":"1.822","low":"1.780","close":"1.790","volume":"1984135408"},{"day":"2024-04-12","open":"1.785","high":"1.789","low":"1.711","close":"1.713","volume":"3375917609"},{"day":"2024-04-19","open":"1.712","high":"1.759","low":"1.692","close":"1.705","volume":"4089972893"},{"day":"2024-04-26","open":"1.695","high":"1.777","low":"1.687","close":"1.774","volume":"3170914203"},{"day":"2024-04-30","open":"1.780","high":"1.854","low":"1.780","close":"1.816","volume":"1948914827"},{"day":"2024-05-10","open":"1.852","high":"1.863","low":"1.820","close":"1.840","volume":"3410823190"},{"day":"2024-05-17","open":"1.819","high":"1.835","low":"1.791","close":"1.824","volume":"3072539046"},{"day":"2024-05-24","open":"1.828","high":"1.844","low":"1.778","close":"1.781","volume":"3360220019"},{"day":"2024-05-31","open":"1.784","high":"1.794","low":"1.762","close":"1.772","volume":"2704863955"},{"day":"2024-06-07","open":"1.769","high":"1.821","low":"1.729","close":"1.748","volume":"3487834679"},{"day":"2024-06-14","open":"1.735","high":"1.766","low":"1.726","close":"1.756","volume":"2371085451"},{"day":"2024-06-21","open":"1.746","high":"1.785","low":"1.709","close":"1.723","volume":"2932439685"},{"day":"2024-06-28","open":"1.711","high":"1.721","low":"1.647","close":"1.652","volume":"3869228619"},{"day":"2024-07-05","open":"1.648","high":"1.658","low":"1.601","close":"1.623","volume":"3833069636"},{"day":"2024-07-12","open":"1.615","high":"1.664","low":"1.584","close":"1.653","volume":"4470413038"},{"day":"2024-07-19","open":"1.644","high":"1.699","low":"1.633","close":"1.692","volume":"6001306543"},{"day":"2024-07-26","open":"1.693","high":"1.702","low":"1.607","close":"1.627","volume":"3520159751"},{"day":"2024-08-02","open":"1.622","high":"1.663","low":"1.591","close":"1.609","volume":"4637166382"},{"day":"2024-08-09","open":"1.592","high":"1.625","low":"1.566","close":"1.566","volume":"4553442487"},{"day":"2024-08-16","open":"1.566","high":"1.579","low":"1.550","close":"1.561","volume":"4325460432"},{"day":"2024-08-23","open":"1.560","high":"1.577","low":"1.509","close":"1.517","volume":"4530647149"},{"day":"2024-08-30","open":"1.517","high":"1.571","low":"1.484","close":"1.552","volume":"6195833982"},{"day":"2024-09-06","open":"1.547","high":"1.552","low":"1.503","close":"1.508","volume":"5518900156"},{"day":"2024-09-13","open":"1.500","high":"1.549","low":"1.495","close":"1.509","volume":"6930216948"},{"day":"2024-09-20","open":"1.505","high":"1.537","low":"1.492","close":"1.508","volume":"4897196910"},{"day":"2024-09-27","open":"1.507","high":"1.890","low":"1.500","close":"1.860","volume":"15771087688"},{"day":"2024-09-30","open":"2.000","high":"2.232","low":"1.928","close":"2.232","volume":"6977214473"},{"day":"2024-10-11","open":"2.678","high":"2.678","low":"2.026","close":"2.060","volume":"50391688234"},{"day":"2024-10-18","open":"2.078","high":"2.256","low":"1.986","close":"2.156","volume":"25199783192"},{"day":"2024-10-25","open":"2.162","high":"2.236","low":"2.126","close":"2.196","volume":"17252762497"},{"day":"2024-11-01","open":"2.193","high":"2.198","low":"2.080","close":"2.084","volume":"10149343130"},{"day":"2024-11-08","open":"2.081","high":"2.365","low":"2.080","close":"2.282","volume":"19031806659"},{"day":"2024-11-15","open":"2.250","high":"2.402","low":"2.201","close":"2.204","volume":"14153944130"},{"day":"2024-11-22","open":"2.205","high":"2.240","low":"2.132","close":"2.136","volume":"11987943156"},{"day":"2024-11-29","open":"2.140","high":"2.221","low":"2.079","close":"2.179","volume":"10415037324"},{"day":"2024-12-06","open":"2.172","high":"2.247","low":"2.161","close":"2.224","volume":"8753306059"},{"day":"2024-12-13","open":"2.219","high":"2.320","low":"2.185","close":"2.193","volume":"10156909764"},{"day":"2024-12-20","open":"2.190","high":"2.192","low":"2.132","close":"2.169","volume":"6728448750"},{"day":"2024-12-27","open":"2.163","high":"2.192","low":"2.142","close":"2.163","volume":"6566649400"},{"day":"2025-01-03","open":"2.158","high":"2.174","low":"1.976","close":"1.978","volume":"7241625550"},{"day":"2025-01-10","open":"1.978","high":"1.994","low":"1.925","close":"1.938","volume":"8213171461"},{"day":"2025-01-17","open":"1.916","high":"2.044","low":"1.916","close":"2.026","volume":"9478883694"},{"day":"2025-01-24","open":"2.047","high":"2.110","low":"2.041","close":"2.084","volume":"7351014078"},{"day":"2025-01-27","open":"2.086","high":"2.087","low":"2.028","close":"2.028","volume":"1424693201"},{"day":"2025-02-07","open":"2.043","high":"2.159","low":"2.016","close":"2.131","volume":"5553740801"},{"day":"2025-02-14","open":"2.140","high":"2.181","low":"2.101","close":"2.174","volume":"7608781170"},{"day":"2025-02-21","open":"2.198","high":"2.242","low":"2.131","close":"2.239","volume":"7193854362"},{"day":"2025-02-28","open":"2.232","high":"2.240","low":"2.123","close":"2.128","volume":"7582337229"},{"day":"2025-03-07","open":"2.133","high":"2.200","low":"2.120","close":"2.160","volume":"7069488299"},{"day":"2025-03-14","open":"2.166","high":"2.190","low":"2.113","close":"2.186","volume":"6290429190"},{"day":"2025-03-21","open":"2.188","high":"2.201","low":"2.108","close":"2.112","volume":"5387474362"},{"day":"2025-03-28","open":"2.110","high":"2.125","low":"2.076","close":"2.089","volume":"4511390540"},{"day":"2025-04-03","open":"2.079","high":"2.087","low":"2.018","close":"2.027","volume":"4455267115"},{"day":"2025-04-11","open":"1.930","high":"1.931","low":"1.721","close":"1.892","volume":"17843301392"},{"day":"2025-04-18","open":"1.915","high":"1.919","low":"1.844","close":"1.878","volume":"6023110770"},{"day":"2025-04-25","open":"1.874","high":"1.933","low":"1.865","close":"1.920","volume":"6038929039"},{"day":"2025-04-30","open":"1.918","high":"1.926","low":"1.895","close":"1.921","volume":"2444192655"},{"day":"2025-05-09","open":"1.936","high":"2.007","low":"1.935","close":"1.984","volume":"5175705545"},{"day":"2025-05-16","open":"2.013","high":"2.074","low":"2.005","close":"2.008","volume":"5322809423"},{"day":"2025-05-23","open":"2.006","high":"2.047","low":"1.988","close":"1.994","volume":"3835345455"},{"day":"2025-05-30","open":"1.990","high":"1.997","low":"1.956","close":"1.972","volume":"3814605481"},{"day":"2025-06-06","open":"1.961","high":"2.029","low":"1.960","close":"2.017","volume":"2637990512"},{"day":"2025-06-13","open":"2.020","high":"2.053","low":"1.999","close":"2.020","volume":"3998996585"},{"day":"2025-06-20","open":"2.019","high":"2.041","low":"1.987","close":"1.988","volume":"2707637297"},{"day":"2025-06-27","open":"1.980","high":"2.125","low":"1.975","close":"2.101","volume":"5720657867"},{"day":"2025-07-04","open":"2.110","high":"2.167","low":"2.097","close":"2.133","volume":"4546980911"},{"day":"2025-07-11","open":"2.126","high":"2.202","low":"2.106","close":"2.185","volume":"5132104194"},{"day":"2025-07-18","open":"2.180","high":"2.274","low":"2.167","close":"2.252","volume":"4800517596"},{"day":"2025-07-25","open":"2.258","high":"2.326","low":"2.251","close":"2.318","volume":"5098893372"},{"day":"2025-08-01","open":"2.322","high":"2.384","low":"2.281","close":"2.303","volume":"6819908079"},{"day":"2025-08-08","open":"2.285","high":"2.350","low":"2.282","close":"2.312","volume":"4530454927"},{"day":"2025-08-15","open":"2.317","high":"2.518","low":"2.312","close":"2.509","volume":"7085886356"},{"day":"2025-08-22","open":"2.520","high":"2.663","low":"2.504","close":"2.662","volume":"10040498008"},{"day":"2025-08-29","open":"2.693","high":"2.909","low":"2.675","close":"2.865","volume":"12944805304"},{"day":"2025-09-05","open":"2.880","high":"2.954","low":"2.716","close":"2.944","volume":"14249705774"},{"day":"2025-09-12","open":"2.946","high":"3.033","low":"2.818","close":"2.995","volume":"10816232564"},{"day":"2025-09-19","open":"3.006","high":"3.141","low":"2.993","close":"3.062","volume":"9702349250"},{"day":"2025-09-26","open":"3.068","high":"3.240","low":"3.015","close":"3.129","volume":"8877559979"},{"day":"2025-09-30","open":"3.126","high":"3.254","low":"3.126","close":"3.217","volume":"2873018305"},{"day":"2025-10-10","open":"3.217","high":"3.297","low":"3.072","close":"3.095","volume":"3971209693"},{"day":"2025-10-17","open":"2.952","high":"3.106","low":"2.905","close":"2.915","volume":"9613710859"},{"day":"2025-10-24","open":"2.976","high":"3.147","low":"2.948","close":"3.147","volume":"6960197014"},{"day":"2025-10-31","open":"3.209","high":"3.308","low":"3.155","close":"3.166","volume":"7135660687"},{"day":"2025-11-07","open":"3.152","high":"3.218","low":"3.046","close":"3.185","volume":"6187688138"},{"day":"2025-11-14","open":"3.200","high":"3.215","low":"3.058","close":"3.093","volume":"6237085304"},{"day":"2025-11-21","open":"3.074","high":"3.113","low":"2.903","close":"2.904","volume":"7322895026"},{"day":"2025-11-28","open":"2.925","high":"3.093","low":"2.873","close":"3.035","volume":"7680885191"},{"day":"2025-12-05","open":"3.044","high":"3.098","low":"2.997","close":"3.089","volume":"4086302437"},{"day":"2025-12-12","open":"3.101","high":"3.226","low":"3.099","close":"3.174","volume":"5150894829"},{"day":"2025-12-19","open":"3.140","high":"3.167","low":"3.043","close":"3.107","volume":"6142126089"},{"day":"2025-12-26","open":"3.135","high":"3.252","low":"3.135","close":"3.226","volume":"4890746224"},{"day":"2025-12-31","open":"3.217","high":"3.239","low":"3.182","close":"3.186","volume":"2850928432"},{"day":"2026-01-09","open":"3.215","high":"3.336","low":"3.210","close":"3.314","volume":"6286742861"},{"day":"2026-01-16","open":"3.314","high":"3.402","low":"3.267","close":"3.346","volume":"14978237301"}]